autoreduce_rest_api/__init__.py
autoreduce_rest_api/manage.py
autoreduce_rest_api/pytest.ini
autoreduce_rest_api/autoreduce_django/__init__.py
autoreduce_rest_api/autoreduce_django/asgi.py
autoreduce_rest_api/autoreduce_django/settings.py
autoreduce_rest_api/autoreduce_django/urls.py
autoreduce_rest_api/autoreduce_django/wsgi.py
autoreduce_rest_api/autoreduce_django/fixtures/software_fixture.json
autoreduce_rest_api/autoreduce_django/fixtures/status_fixture.json
autoreduce_rest_api/autoreduce_django/fixtures/super_user_fixture.json
autoreduce_rest_api/runs/__init__.py
autoreduce_rest_api/runs/urls.py
autoreduce_rest_api/runs/views.py
autoreduce_rest_api/runs/test/__init__.py
autoreduce_rest_api/runs/test/test_submit_runs.py
autoreduce_rest_api-22.0.0.dev23.dist-info/LICENSE.txt
autoreduce_rest_api-22.0.0.dev23.dist-info/METADATA
autoreduce_rest_api-22.0.0.dev23.dist-info/WHEEL
autoreduce_rest_api-22.0.0.dev23.dist-info/entry_points.txt
autoreduce_rest_api-22.0.0.dev23.dist-info/top_level.txt
autoreduce_rest_api-22.0.0.dev23.dist-info/RECORD
