Metadata-Version: 2.1
Name: autoreduce-rest-api
Version: 22.0.0.dev23
Summary: ISIS Autoreduction Runs REST API
License: GNU General Public License
Project-URL: Repository, https://github.com/autoreduction/rest-api
Project-URL: Wiki, https://github.com/autoreduction/queue-processor/wiki
Classifier: Framework :: Django
Classifier: Programming Language :: Python :: 3
License-File: LICENSE.txt
Requires-Dist: autoreduce-scripts (==22.0.0.dev44)
Requires-Dist: Django (==4.0.6)
Requires-Dist: djangorestframework (==3.13.1)
Requires-Dist: django-hurricane
Provides-Extra: dev
Requires-Dist: autoreduce-qp (>=22.0.0.dev38) ; extra == 'dev'
Requires-Dist: mysqlclient (==2.1.0) ; extra == 'dev'
Requires-Dist: parameterized (==0.8.1) ; extra == 'dev'
